spm_release_tracker/__init__.py
spm_release_tracker/spm_release_tracker.py
spm_release_tracker/version.py
spm_release_tracker-0.0.3.dist-info/LICENSE
spm_release_tracker-0.0.3.dist-info/METADATA
spm_release_tracker-0.0.3.dist-info/WHEEL
spm_release_tracker-0.0.3.dist-info/entry_points.txt
spm_release_tracker-0.0.3.dist-info/top_level.txt
spm_release_tracker-0.0.3.dist-info/RECORD
