Metadata-Version: 2.1
Name: spm_release_tracker
Version: 0.0.3
License-File: LICENSE
Requires-Dist: requests
Requires-Dist: rich
Requires-Dist: argparse
Requires-Dist: requests-cache
Requires-Dist: pytz
